Ejercicio2/Ejercicio2.v
module BufferTriEstado4bits (input wire enable, input wire [3:0 ] IN, output [3:0] OUT); 

assign OUT = enable ? IN : 4'bz;

endmodule

module ALU (input wire [3:0]A, input wire [3:0]B, input wire [2:0]Sel, input wire reset, output reg [3:0]Y, output reg Z, output reg C); 
reg [4:0] P;

	always @ (A or B or Sel) 
		case (Sel) 
			0 : begin
					Y = A;
					P = 5'b00000;
					begin
						C <= P[4];
					end
				end
			1 :  begin
					P = A - B; 
					Y[0] = P[0];
					Y[1] = P[1];
					Y[2] = P[2];
					Y[3] = P[3];
					begin
						C <= P[4];
					end
				end
			2 : begin
					Y = B;
					P = 5'b00000;
					begin
						C <= P[4];
					end
				end
			3 : begin
					P = A + B; 
					Y[0] = P[0];
					Y[1] = P[1];
					Y[2] = P[2];
					Y[3] = P[3];
					begin
						C <= P[4];
					end
				end
			4 :begin
					Y = ~(A & B);
					P = 5'b00000;
					begin
						C <= P[4];
					end
				end
			
			default : $display("Error in Sel"); 
		endcase 
	
	
	always @(Y or posedge reset)  
		begin
			if(Y == 4'b0000 )
				begin
					Z <= 1; 
				end
			else if (reset)
				begin
					P <= 5'b00000;
				end
			else 
				begin
					Z <= 0;
				end
		end

endmodule

module FLipFlopD4bits(input wire [3:0] D,input wire clk,input wire reset, input wire enable,output [3:0] Q);
reg Q;
	always @(posedge clk or posedge reset)  
		begin
			if(reset)
				begin
					Q <= 0; 
				end
			else if(enable==1) 
				begin
					Q <= D;
				end
			else
				begin
					Q <= Q;
		end
	end
endmodule 

module Ejercicio_2(input wire[3:0]IN, input wire[2:0]Sel, input wire clk, input wire reset, input wire enableACCU, input wire enableBTE1, input wire enableBTE2, output[3:0]Y, output Z, output C);

wire [3:0] OUT_BTE1;
wire [3:0] OUT_ACCU;
wire [3:0] OUT_ALU;

BufferTriEstado4bits	BTE1 (enableBTE1, IN, OUT_BTE1);
ALU						ALU1 (OUT_ACCU, OUT_BTE1, Sel, reset, OUT_ALU, Z, C);
FLipFlopD4bits			ACCU (OUT_ALU, clk, reset, enableACCU, OUT_ACCU);
BufferTriEstado4bits	BTE2 (enableBTE2, OUT_ALU, Y);

endmodule

Ejercicio2/Ejercicio2_tb.v
module Ejercicio2_tb();

reg clk, enableACCU, enableBTE1, enableBTE2, reset; 
reg  [2:0] Sel;
reg [3:0] IN;
wire Z, C; 
wire [3:0] Y; 

Ejercicio_2 E2 (IN, Sel, clk, reset, enableACCU, enableBTE1, enableBTE2, Y, Z, C);

initial begin
	clk=1;
	forever #5 clk = ~clk;  
end 

initial begin

	#1 $display("");
	$display("Ejercicio 2");
    $display("RESET ENABLE_ACCU ENABLE_BTE1 ENABLE_BTE2 SELECT ENTRADA | CARRY_FLAG ZERO_FLAG SALIDA");
    $display("---------------------------------------------------------|----------------------------");
    $monitor("%d           %d           %d           %d        %d     %d    |      %d         %d       %d ", reset, enableACCU, enableBTE1, enableBTE2, Sel, IN, C, Z, Y);
	   
	#2 reset = 1; enableACCU = 0; enableBTE1 = 0; enableBTE2 = 0; Sel = 3'b000; IN = 2'b00;
	#5 reset = 0;
	//SE INGRESA EL VALOR DE ENTRADA "5"
	#10 IN = 5;
	//SE HABILITA EL PASO DEL VALOR POR EL BUFFER 1 Y POR LA ALU
	#10 enableBTE1 = 1; Sel = 2;
	//SE HABILITA EL PASO POR EL ACUMULADOR
	#10 enableACCU = 1; 
	//SE CIERRA EL PASO AL ACUMULADOR, SE CIEERA EL PASO POR EL BUFFER 1, SE INGRESA EL VALOR DE ENTRADA "0" 
	#10 enableACCU = 0; enableBTE1 = 0; IN = 0; 
	//SE VA A DEJAR FIJO EL VALOR EN EL ACUMULADOR, SE SELECCIONA EL MODO DE SUMA DE LA ALU Y SE VA A SUMAR CON LOS NUMEROS DEL 0 AL 15
	#10 enableBTE1 = 1; enableBTE2 = 1; Sel = 3;
	#10 IN = 1;
	#10 IN = 2;
	#10 IN = 3;
	#10 IN = 4;
	#10 IN = 5;
	#10 IN = 6;
	#10 IN = 7;
	#10 IN = 8;
	#10 IN = 9;
	#10 IN = 10;
	#10 IN = 11;
	#10 IN = 12;
	#10 IN = 13;
	#10 IN = 14;
	#10 IN = 15;
	//SE INGRESA EL VALOR DE ENTRADA "12" Y SE LE PERMITE EL PASO HASTA EL ACUMULADOR
	#10 IN = 12; enableBTE1 = 1; Sel = 2; enableACCU = 1; enableBTE2 = 0;
	//SE ABRE EL PASO DEL ACUMULADOR A LA SALIDA, SE CIERRA EL PASO AL ACUMULADOR, SE CIEERA EL PASO POR EL BUFFER 1, SE INGRESA EL VALOR DE ENTRADA "0" 
	#10 enableACCU = 0; enableBTE1 = 0; IN = 0; Sel = 0; enableBTE2 = 1;
	//SE PERMITE EL PASO POR EL BUFFER 1, SE SELECCIONA EL MODO DE RESTA DE LA ALU Y SE RESTARÁN LOS VALORES DEL 0 AL 15
	#10 enableBTE1 = 1; Sel = 1;
	#10 IN = 1;
	#10 IN = 2;
	#10 IN = 3;
	#10 IN = 4;
	#10 IN = 5;
	#10 IN = 6;
	#10 IN = 7;
	#10 IN = 8;
	#10 IN = 9;
	#10 IN = 10;
	#10 IN = 11;
	#10 IN = 12;
	#10 IN = 13;
	#10 IN = 14;
	#10 IN = 15;
	//SE INGRESA EL VALOR DE ENTRADA "8" Y SE LE PERMITE EL PASO HASTA EL ACUMULADOR
	#10 IN = 8; enableBTE1 = 1; Sel = 2; enableACCU = 1; enableBTE2 = 0;
	//SE ABRE EL PASO DEL ACUMULADOR A LA SALIDA, SE CIERRA EL PASO AL ACUMULADOR, SE CIEERA EL PASO POR EL BUFFER 1, SE INGRESA EL VALOR DE ENTRADA "0" 
	#10 enableACCU = 0; enableBTE1 = 0; IN = 0; Sel = 0; enableBTE2 = 1;
	//SE PERMITE EL PASO POR EL BUFFER 1, SE SELECCIONA EL MODO DE NAND DE LA ALU Y SE COMPARA EL ACUMULADOR CON LOS VALORES DEL 0 AL 15
	#10 enableBTE1 = 1; Sel = 4;
	#10 IN = 1;
	#10 IN = 2;
	#10 IN = 3;
	#10 IN = 4;
	#10 IN = 5;
	#10 IN = 6;
	#10 IN = 7;
	#10 IN = 8;
	#10 IN = 9;
	#10 IN = 10;
	#10 IN = 11;
	#10 IN = 12;
	#10 IN = 13;
	#10 IN = 14;
	#10 IN = 15;
	
	#10 $display("");
 end
 
initial
#580 $finish; 

initial begin
    $dumpfile("Ejercicio2_tb.vcd");
    $dumpvars(0, Ejercicio2_tb);
end

endmodule

Ejercicio2/Ejercicio2_tb.vcd
$date
	Fri Nov 06 05:56:55 2020
$end
$version
	Icarus Verilog
$end
$timescale
	1ps
$end
$scope module Ejercicio2_tb $end
$var wire 1 ! Z $end
$var wire 4 " Y [3:0] $end
$var wire 1 # C $end
$var reg 4 $ IN [3:0] $end
$var reg 3 % Sel [2:0] $end
$var reg 1 & clk $end
$var reg 1 ' enableACCU $end
$var reg 1 ( enableBTE1 $end
$var reg 1 ) enableBTE2 $end
$var reg 1 * reset $end
$scope module E2 $end
$var wire 4 + IN [3:0] $end
$var wire 3 , Sel [2:0] $end
$var wire 1 & clk $end
$var wire 1 ' enableACCU $end
$var wire 1 ( enableBTE1 $end
$var wire 1 ) enableBTE2 $end
$var wire 1 * reset $end
$var wire 1 ! Z $end
$var wire 4 - Y [3:0] $end
$var wire 4 . OUT_BTE1 [3:0] $end
$var wire 4 / OUT_ALU [3:0] $end
$var wire 4 0 OUT_ACCU [3:0] $end
$var wire 1 # C $end
$scope module ACCU $end
$var wire 1 & clk $end
$var wire 1 ' enable $end
$var wire 1 * reset $end
$var wire 4 1 D [3:0] $end
$var reg 4 2 Q [3:0] $end
$upscope $end
$scope module ALU1 $end
$var wire 4 3 A [3:0] $end
$var wire 3 4 Sel [2:0] $end
$var wire 1 * reset $end
$var wire 4 5 B [3:0] $end
$var reg 1 # C $end
$var reg 5 6 P [4:0] $end
$var reg 4 7 Y [3:0] $end
$var reg 1 ! Z $end
$upscope $end
$scope module BTE1 $end
$var wire 4 8 IN [3:0] $end
$var wire 1 ( enable $end
$var wire 4 9 OUT [3:0] $end
$upscope $end
$scope module BTE2 $end
$var wire 4 : IN [3:0] $end
$var wire 1 ) enable $end
$var wire 4 ; OUT [3:0] $end
$upscope $end
$upscope $end
$upscope $end
$enddefinitions $end
#0
$dumpvars
bx ;
bx :
bx 9
bx 8
bx 7
bx 6
bx 5
bx 4
bx 3
bx 2
bx 1
bx 0
bx /
bx .
bx -
bx ,
bx +
x*
x)
x(
x'
1&
bx %
bx $
x#
bx "
x!
$end
#3
1!
b0 /
b0 1
b0 7
b0 :
0#
b0 0
b0 2
b0 3
b0 6
bz "
bz -
bz ;
bz .
bz 5
bz 9
b0 $
b0 +
b0 8
b0 %
b0 ,
b0 4
0)
0(
0'
1*
#5
0&
#8
0*
#10
1&
#15
0&
#18
b101 $
b101 +
b101 8
#20
1&
#25
0&
#28
0!
b101 /
b101 1
b101 7
b101 :
b101 .
b101 5
b101 9
b10 %
b10 ,
b10 4
1(
#30
1&
#35
0&
#38
1'
#40
b101 0
b101 2
b101 3
1&
#45
0&
#48
bz /
bz 1
bz 7
bz :
bz .
bz 5
bz 9
b0 $
b0 +
b0 8
0(
0'
#50
1&
#55
0&
#58
b101 "
b101 -
b101 ;
b101 /
b101 1
b101 7
b101 :
b101 6
b0 .
b0 5
b0 9
b11 %
b11 ,
b11 4
1)
1(
#60
1&
#65
0&
#68
b110 "
b110 -
b110 ;
b110 /
b110 1
b110 7
b110 :
b110 6
b1 .
b1 5
b1 9
b1 $
b1 +
b1 8
#70
1&
#75
0&
#78
b111 "
b111 -
b111 ;
b111 /
b111 1
b111 7
b111 :
b111 6
b10 .
b10 5
b10 9
b10 $
b10 +
b10 8
#80
1&
#85
0&
#88
b1000 "
b1000 -
b1000 ;
b1000 /
b1000 1
b1000 7
b1000 :
b1000 6
b11 .
b11 5
b11 9
b11 $
b11 +
b11 8
#90
1&
#95
0&
#98
b1001 "
b1001 -
b1001 ;
b1001 /
b1001 1
b1001 7
b1001 :
b1001 6
b100 .
b100 5
b100 9
b100 $
b100 +
b100 8
#100
1&
#105
0&
#108
b1010 "
b1010 -
b1010 ;
b1010 /
b1010 1
b1010 7
b1010 :
b1010 6
b101 .
b101 5
b101 9
b101 $
b101 +
b101 8
#110
1&
#115
0&
#118
b1011 "
b1011 -
b1011 ;
b1011 /
b1011 1
b1011 7
b1011 :
b1011 6
b110 .
b110 5
b110 9
b110 $
b110 +
b110 8
#120
1&
#125
0&
#128
b1100 "
b1100 -
b1100 ;
b1100 /
b1100 1
b1100 7
b1100 :
b1100 6
b111 .
b111 5
b111 9
b111 $
b111 +
b111 8
#130
1&
#135
0&
#138
b1101 "
b1101 -
b1101 ;
b1101 /
b1101 1
b1101 7
b1101 :
b1101 6
b1000 .
b1000 5
b1000 9
b1000 $
b1000 +
b1000 8
#140
1&
#145
0&
#148
b1110 "
b1110 -
b1110 ;
b1110 /
b1110 1
b1110 7
b1110 :
b1110 6
b1001 .
b1001 5
b1001 9
b1001 $
b1001 +
b1001 8
#150
1&
#155
0&
#158
b1111 "
b1111 -
b1111 ;
b1111 /
b1111 1
b1111 7
b1111 :
b1111 6
b1010 .
b1010 5
b1010 9
b1010 $
b1010 +
b1010 8
#160
1&
#165
0&
#168
1!
1#
b0 "
b0 -
b0 ;
b0 /
b0 1
b0 7
b0 :
b10000 6
b1011 .
b1011 5
b1011 9
b1011 $
b1011 +
b1011 8
#170
1&
#175
0&
#178
0!
b1 "
b1 -
b1 ;
b1 /
b1 1
b1 7
b1 :
b10001 6
b1100 .
b1100 5
b1100 9
b1100 $
b1100 +
b1100 8
#180
1&
#185
0&
#188
b10 "
b10 -
b10 ;
b10 /
b10 1
b10 7
b10 :
b10010 6
b1101 .
b1101 5
b1101 9
b1101 $
b1101 +
b1101 8
#190
1&
#195
0&
#198
b11 "
b11 -
b11 ;
b11 /
b11 1
b11 7
b11 :
b10011 6
b1110 .
b1110 5
b1110 9
b1110 $
b1110 +
b1110 8
#200
1&
#205
0&
#208
b100 "
b100 -
b100 ;
b100 /
b100 1
b100 7
b100 :
b10100 6
b1111 .
b1111 5
b1111 9
b1111 $
b1111 +
b1111 8
#210
1&
#215
0&
#218
0#
bz "
bz -
bz ;
b0 6
b1100 /
b1100 1
b1100 7
b1100 :
b1100 .
b1100 5
b1100 9
0)
1'
b10 %
b10 ,
b10 4
b1100 $
b1100 +
b1100 8
#220
b1100 0
b1100 2
b1100 3
1&
#225
0&
#228
b1100 "
b1100 -
b1100 ;
bz .
bz 5
bz 9
1)
b0 %
b0 ,
b0 4
b0 $
b0 +
b0 8
0(
0'
#230
1&
#235
0&
#238
b1100 6
b0 .
b0 5
b0 9
b1 %
b1 ,
b1 4
1(
#240
1&
#245
0&
#248
b1011 "
b1011 -
b1011 ;
b1011 /
b1011 1
b1011 7
b1011 :
b1011 6
b1 .
b1 5
b1 9
b1 $
b1 +
b1 8
#250
1&
#255
0&
#258
b1010 "
b1010 -
b1010 ;
b1010 /
b1010 1
b1010 7
b1010 :
b1010 6
b10 .
b10 5
b10 9
b10 $
b10 +
b10 8
#260
1&
#265
0&
#268
b1001 "
b1001 -
b1001 ;
b1001 /
b1001 1
b1001 7
b1001 :
b1001 6
b11 .
b11 5
b11 9
b11 $
b11 +
b11 8
#270
1&
#275
0&
#278
b1000 "
b1000 -
b1000 ;
b1000 /
b1000 1
b1000 7
b1000 :
b1000 6
b100 .
b100 5
b100 9
b100 $
b100 +
b100 8
#280
1&
#285
0&
#288
b111 "
b111 -
b111 ;
b111 /
b111 1
b111 7
b111 :
b111 6
b101 .
b101 5
b101 9
b101 $
b101 +
b101 8
#290
1&
#295
0&
#298
b110 "
b110 -
b110 ;
b110 /
b110 1
b110 7
b110 :
b110 6
b110 .
b110 5
b110 9
b110 $
b110 +
b110 8
#300
1&
#305
0&
#308
b101 "
b101 -
b101 ;
b101 /
b101 1
b101 7
b101 :
b101 6
b111 .
b111 5
b111 9
b111 $
b111 +
b111 8
#310
1&
#315
0&
#318
b100 "
b100 -
b100 ;
b100 /
b100 1
b100 7
b100 :
b100 6
b1000 .
b1000 5
b1000 9
b1000 $
b1000 +
b1000 8
#320
1&
#325
0&
#328
b11 "
b11 -
b11 ;
b11 /
b11 1
b11 7
b11 :
b11 6
b1001 .
b1001 5
b1001 9
b1001 $
b1001 +
b1001 8
#330
1&
#335
0&
#338
b10 "
b10 -
b10 ;
b10 /
b10 1
b10 7
b10 :
b10 6
b1010 .
b1010 5
b1010 9
b1010 $
b1010 +
b1010 8
#340
1&
#345
0&
#348
b1 "
b1 -
b1 ;
b1 /
b1 1
b1 7
b1 :
b1 6
b1011 .
b1011 5
b1011 9
b1011 $
b1011 +
b1011 8
#350
1&
#355
0&
#358
1!
b0 "
b0 -
b0 ;
b0 /
b0 1
b0 7
b0 :
b0 6
b1100 .
b1100 5
b1100 9
b1100 $
b1100 +
b1100 8
#360
1&
#365
0&
#368
0!
1#
b1111 "
b1111 -
b1111 ;
b1111 /
b1111 1
b1111 7
b1111 :
b11111 6
b1101 .
b1101 5
b1101 9
b1101 $
b1101 +
b1101 8
#370
1&
#375
0&
#378
b1110 "
b1110 -
b1110 ;
b1110 /
b1110 1
b1110 7
b1110 :
b11110 6
b1110 .
b1110 5
b1110 9
b1110 $
b1110 +
b1110 8
#380
1&
#385
0&
#388
b1101 "
b1101 -
b1101 ;
b1101 /
b1101 1
b1101 7
b1101 :
b11101 6
b1111 .
b1111 5
b1111 9
b1111 $
b1111 +
b1111 8
#390
1&
#395
0&
#398
0#
bz "
bz -
bz ;
b0 6
b1000 /
b1000 1
b1000 7
b1000 :
b1000 .
b1000 5
b1000 9
0)
1'
b10 %
b10 ,
b10 4
b1000 $
b1000 +
b1000 8
#400
b1000 0
b1000 2
b1000 3
1&
#405
0&
#408
b1000 "
b1000 -
b1000 ;
bz .
bz 5
bz 9
1)
b0 %
b0 ,
b0 4
b0 $
b0 +
b0 8
0(
0'
#410
1&
#415
0&
#418
b1111 "
b1111 -
b1111 ;
b1111 /
b1111 1
b1111 7
b1111 :
b0 .
b0 5
b0 9
b100 %
b100 ,
b100 4
1(
#420
1&
#425
0&
#428
b1 .
b1 5
b1 9
b1 $
b1 +
b1 8
#430
1&
#435
0&
#438
b10 .
b10 5
b10 9
b10 $
b10 +
b10 8
#440
1&
#445
0&
#448
b11 .
b11 5
b11 9
b11 $
b11 +
b11 8
#450
1&
#455
0&
#458
b100 .
b100 5
b100 9
b100 $
b100 +
b100 8
#460
1&
#465
0&
#468
b101 .
b101 5
b101 9
b101 $
b101 +
b101 8
#470
1&
#475
0&
#478
b110 .
b110 5
b110 9
b110 $
b110 +
b110 8
#480
1&
#485
0&
#488
b111 .
b111 5
b111 9
b111 $
b111 +
b111 8
#490
1&
#495
0&
#498
b111 "
b111 -
b111 ;
b111 /
b111 1
b111 7
b111 :
b1000 .
b1000 5
b1000 9
b1000 $
b1000 +
b1000 8
#500
1&
#505
0&
#508
b1001 .
b1001 5
b1001 9
b1001 $
b1001 +
b1001 8
#510
1&
#515
0&
#518
b1010 .
b1010 5
b1010 9
b1010 $
b1010 +
b1010 8
#520
1&
#525
0&
#528
b1011 .
b1011 5
b1011 9
b1011 $
b1011 +
b1011 8
#530
1&
#535
0&
#538
b1100 .
b1100 5
b1100 9
b1100 $
b1100 +
b1100 8
#540
1&
#545
0&
#548
b1101 .
b1101 5
b1101 9
b1101 $
b1101 +
b1101 8
#550
1&
#555
0&
#558
b1110 .
b1110 5
b1110 9
b1110 $
b1110 +
b1110 8
#560
1&
#565
0&
#568
b1111 .
b1111 5
b1111 9
b1111 $
b1111 +
b1111 8
