Ejercicio1/Ejercicio1.v
module Contador12bits(input wire [11:0] Load, input clk, input enable, input reset, output [11:0] Q);
reg Q;

always @(posedge clk or posedge reset or Load)  
			begin
				if(reset)
					begin
						Q <= 12'b000000000000; 
					end
				else if(Load)
					begin
						Q <= Load; 
					end
				else if(enable == 1)
					begin
						Q <= Q+1;
					end
				else
					begin
						Q <= Q;
					end
						
			end
endmodule 


module ROM4kx8 (input wire [11:0]Address, output wire [7:0]Data);           
	reg [11:0] ROM [0:4095] ;  
    
	assign Data = ROM[Address];

initial begin
  $readmemb("Lista.txt", ROM); 
end

endmodule

module FLipFlopD4bits(input wire [3:0] D,input wire clk,input wire reset, input wire enable,output [3:0] Q);
reg Q;
	always @(posedge clk or posedge reset)  
		begin
			if(reset)
				begin
					Q <= 0; 
				end
			else if(enable==1) 
				begin
					Q <= D;
				end
			else
				begin
					Q <= Q;
		end
	end
endmodule 

module Fetch (input wire [7:0] D, input wire clk, input wire reset, input wire enable, output [3:0] Instr, output [3:0] Oprnd);

FLipFlopD4bits FFD_1(D[7:4], clk, reset, enable, Instr);
FLipFlopD4bits FFD_2(D[3:0], clk, reset, enable, Oprnd);

endmodule

module Ejercicio_1 (input wire [11:0] Load, input wire clk, input wire reset, input wire enablePG, input wire enableFTCH, output [3:0] Instr, output [3:0] Oprnd);

wire [11:0] No_Instruccion;
wire [7:0]  Instruccion;

Contador12bits	ProgramCounter	(Load, clk, enablePG, reset, No_Instruccion);
ROM4kx8 		ProgramROM		(No_Instruccion, Instruccion);
Fetch			Fetch1			(Instruccion, clk, reset, enableFTCH, Instr, Oprnd);

endmodule

Ejercicio1/Ejercicio1_tb.v
module Ejercicio1_tb();

reg clk, enablePG, enableFTCH, reset; 
reg [11:0] Load;
wire [3:0] Instr; 
wire [3:0] Oprnd; 

Ejercicio_1 E1 (Load, clk, reset, enablePG, enableFTCH, Instr, Oprnd);

initial begin
	clk=1;
	forever #5 clk = ~clk;  
end 

initial begin

	#1 $display("");
	$display("Ejercicio 1");
    $display("RESET ENABLE_PG ENABLE_FTCH LOAD | INTRUCCION OPERANDO ");
    $display("---------------------------------|---------------------");
    $monitor("%d         %d          %d     %d  |    %d       %d   ", reset, enablePG, enableFTCH, Load, Instr, Oprnd);
	   
	#2 reset = 1; enablePG = 0; enableFTCH = 0; Load = 12'b000000000000;
	#5 reset = 0;
	
	#10  enablePG = 1; enableFTCH = 0;
	#10  enablePG = 1; enableFTCH = 1;
	#90  Load     = 12'b000000010000;
	#40  Load     = 12'b000000000101;
	#50  enablePG = 0;
	
	#10 $display("");
 end
 
initial
#240 $finish; 

initial begin
    $dumpfile("Ejercicio1_tb.vcd");
    $dumpvars(0, Ejercicio1_tb);
end

endmodule

Ejercicio1/Ejercicio1_tb.vcd
$date
	Thu Nov 05 23:55:59 2020
$end
$version
	Icarus Verilog
$end
$timescale
	1ps
$end
$scope module Ejercicio1_tb $end
$var wire 4 ! Oprnd [3:0] $end
$var wire 4 " Instr [3:0] $end
$var reg 12 # Load [11:0] $end
$var reg 1 $ clk $end
$var reg 1 % enableFTCH $end
$var reg 1 & enablePG $end
$var reg 1 ' reset $end
$scope module E1 $end
$var wire 12 ( Load [11:0] $end
$var wire 1 $ clk $end
$var wire 1 % enableFTCH $end
$var wire 1 & enablePG $end
$var wire 1 ' reset $end
$var wire 4 ) Oprnd [3:0] $end
$var wire 12 * No_Instruccion [11:0] $end
$var wire 8 + Instruccion [7:0] $end
$var wire 4 , Instr [3:0] $end
$scope module Fetch1 $end
$var wire 1 $ clk $end
$var wire 1 % enable $end
$var wire 1 ' reset $end
$var wire 4 - Oprnd [3:0] $end
$var wire 4 . Instr [3:0] $end
$var wire 8 / D [7:0] $end
$scope module FFD_1 $end
$var wire 4 0 D [3:0] $end
$var wire 1 $ clk $end
$var wire 1 % enable $end
$var wire 1 ' reset $end
$var reg 4 1 Q [3:0] $end
$upscope $end
$scope module FFD_2 $end
$var wire 4 2 D [3:0] $end
$var wire 1 $ clk $end
$var wire 1 % enable $end
$var wire 1 ' reset $end
$var reg 4 3 Q [3:0] $end
$upscope $end
$upscope $end
$scope module ProgramCounter $end
$var wire 12 4 Load [11:0] $end
$var wire 1 $ clk $end
$var wire 1 & enable $end
$var wire 1 ' reset $end
$var reg 12 5 Q [11:0] $end
$upscope $end
$scope module ProgramROM $end
$var wire 12 6 Address [11:0] $end
$var wire 8 7 Data [7:0] $end
$upscope $end
$upscope $end
$upscope $end
$enddefinitions $end
#0
$dumpvars
bx 7
bx 6
bx 5
bx 4
bx 3
bx 2
bx 1
bx 0
bx /
bx .
bx -
bx ,
bx +
bx *
bx )
bx (
x'
x&
x%
1$
bx #
bx "
bx !
$end
#3
b0 2
b0 0
b0 +
b0 /
b0 7
b0 !
b0 )
b0 -
b0 3
b0 "
b0 ,
b0 .
b0 1
b0 *
b0 5
b0 6
b0 #
b0 (
b0 4
0%
0&
1'
#5
0$
#8
0'
#10
1$
#15
0$
#18
1&
#20
b1 2
b1 +
b1 /
b1 7
b1 *
b1 5
b1 6
1$
#25
0$
#28
1%
#30
b10 2
b10 +
b10 /
b10 7
b1 !
b1 )
b1 -
b1 3
b10 *
b10 5
b10 6
1$
#35
0$
#40
b11 2
b11 +
b11 /
b11 7
b10 !
b10 )
b10 -
b10 3
b11 *
b11 5
b11 6
1$
#45
0$
#50
b100 2
b100 +
b100 /
b100 7
b11 !
b11 )
b11 -
b11 3
b100 *
b100 5
b100 6
1$
#55
0$
#60
b0 2
b1 0
b10000 +
b10000 /
b10000 7
b100 !
b100 )
b100 -
b100 3
b101 *
b101 5
b101 6
1$
#65
0$
#70
b1 2
b10001 +
b10001 /
b10001 7
b1 "
b1 ,
b1 .
b1 1
b0 !
b0 )
b0 -
b0 3
b110 *
b110 5
b110 6
1$
#75
0$
#80
b10 2
b10010 +
b10010 /
b10010 7
b1 !
b1 )
b1 -
b1 3
b111 *
b111 5
b111 6
1$
#85
0$
#90
b11 2
b10011 +
b10011 /
b10011 7
b10 !
b10 )
b10 -
b10 3
b1000 *
b1000 5
b1000 6
1$
#95
0$
#100
b100 2
b10100 +
b10100 /
b10100 7
b11 !
b11 )
b11 -
b11 3
b1001 *
b1001 5
b1001 6
1$
#105
0$
#110
b0 2
b10 0
b100000 +
b100000 /
b100000 7
b100 !
b100 )
b100 -
b100 3
b1010 *
b1010 5
b1010 6
1$
#115
0$
#118
b1 2
b11 0
b110001 +
b110001 /
b110001 7
b10000 *
b10000 5
b10000 6
b10000 #
b10000 (
b10000 4
#120
b1 !
b1 )
b1 -
b1 3
b11 "
b11 ,
b11 .
b11 1
1$
#125
0$
#130
1$
#135
0$
#140
1$
#145
0$
#150
1$
#155
0$
#158
b0 2
b1 0
b10000 +
b10000 /
b10000 7
b101 *
b101 5
b101 6
b101 #
b101 (
b101 4
#160
b0 !
b0 )
b0 -
b0 3
b1 "
b1 ,
b1 .
b1 1
1$
#165
0$
#170
1$
#175
0$
#180
1$
#185
0$
#190
1$
#195
0$
#200
1$
#205
0$
#208
0&
